<?xml version="1.0" encoding="UTF-8"?>
<objects serializationModel="Studio.01.10.00">
    <object class="AudioFile" id="{3f676e99-6442-48c0-9727-5efd53c9e2ce}">
        <property name="assetPath">
            <value>Footstep roupa besouridio 2.wav</value>
        </property>
        <property name="frequencyInKHz">
            <value>44.0999985</value>
        </property>
        <property name="channelCount">
            <value>2</value>
        </property>
        <property name="length">
            <value>0.81750566893424037</value>
        </property>
        <relationship name="masterAssetFolder">
            <destination>{3806f59c-99c7-49c1-9ff9-c9fa55d01af3}</destination>
        </relationship>
    </object>
</objects>
